[
    {
        "fio": "Иван",
        "address": "Кемерово",
        "phone": "+1",
        "created_at": "25-03-2025 04:37:46",
        "products": [
            {
                "id": 1,
                "name": "Пицца Маргарита",
                "quantity": 1,
                "price": 550,
                "sum": 550
            }
        ],
        "all_sum": 550
    },
    {
        "fio": "Anna",
        "address": "Москва",
        "phone": "+2",
        "created_at": "25-03-2025 04:38:18",
        "products": [
            {
                "id": 1,
                "name": "Пицца Маргарита",
                "quantity": 1,
                "price": 550,
                "sum": 550
            }
        ],
        "all_sum": 550
    },
    {
        "fio": "Владислав Анатольевич Милевский",
        "address": "г. Кемерово, ул. Тухачевского, 32",
        "phone": "+8 999 9000 0000",
        "created_at": "25-03-2025 04:47:00",
        "products": [
            {
                "id": 1,
                "name": "Пицца Маргарита",
                "quantity": 1,
                "price": 550,
                "sum": 550
            },
            {
                "id": 2,
                "name": "Пицца Пипперони",
                "quantity": 1,
                "price": 650,
                "sum": 650
            }
        ],
        "all_sum": 1200
    },
    {
        "fio": "Jhon",
        "address": "New Jork",
        "phone": "+7 001004065544",
        "created_at": "25-03-2025 04:49:09",
        "products": [
            {
                "id": 1,
                "name": "Пицца Маргарита",
                "quantity": 1,
                "price": 550,
                "sum": 550
            }
        ],
        "all_sum": 550
    },
    {
        "fio": "FFFFFFFFFF",
        "address": "sdfsdfsdfsdfsdfsdfsdf",
        "phone": "89059000088",
        "email": "a@mail.ru",
        "created_at": "29-03-2025 10:18:23",
        "products": [
            {
                "id": 1,
                "name": "Пицца Маргарита",
                "quantity": 1,
                "price": 550,
                "sum": 550
            }
        ],
        "all_sum": 550
    },
    {
        "fio": "123",
        "address": "канава",
        "phone": "89505855539",
        "email": "123@gmail.com",
        "created_at": "31-03-2025 07:56:42",
        "products": [
            {
                "id": 1,
                "name": "Завтрак Гостиничный",
                "quantity": 1,
                "price": 250,
                "sum": 250
            }
        ],
        "all_sum": 250
    },
    {
        "fio": "123",
        "address": "канава",
        "phone": "89505855539",
        "email": "123@gmail.com",
        "created_at": "31-03-2025 07:56:54",
        "products": [
            {
                "id": 1,
                "name": "Завтрак Гостиничный",
                "quantity": 1,
                "price": 250,
                "sum": 250
            }
        ],
        "all_sum": 250
    },
    {
        "fio": "12312",
        "address": "канава",
        "phone": "89505855539",
        "email": "123@gmail.com",
        "created_at": "31-03-2025 07:58:54",
        "products": [
            {
                "id": 1,
                "name": "Завтрак Гостиничный",
                "quantity": 1,
                "price": 250,
                "sum": 250
            }
        ],
        "all_sum": 250
    }
]